odoo10_addon_stock_lot_note-10.0.1.0.0.99.dev3-py3.8-nspkg.pth
odoo/addons/stock_lot_note/README.rst
odoo/addons/stock_lot_note/__init__.py
odoo/addons/stock_lot_note/__manifest__.py
odoo/addons/stock_lot_note/i18n/stock_lot_note.pot
odoo/addons/stock_lot_note/models/__init__.py
odoo/addons/stock_lot_note/models/stock_production_lot.py
odoo/addons/stock_lot_note/readme/CONTRIBUTORS.rst
odoo/addons/stock_lot_note/readme/DESCRIPTION.rst
odoo/addons/stock_lot_note/readme/USAGE.rst
odoo/addons/stock_lot_note/static/description/icon.png
odoo/addons/stock_lot_note/static/description/index.html
odoo/addons/stock_lot_note/views/stock_production_lot.xml
odoo10_addon_stock_lot_note-10.0.1.0.0.99.dev3.dist-info/METADATA
odoo10_addon_stock_lot_note-10.0.1.0.0.99.dev3.dist-info/WHEEL
odoo10_addon_stock_lot_note-10.0.1.0.0.99.dev3.dist-info/namespace_packages.txt
odoo10_addon_stock_lot_note-10.0.1.0.0.99.dev3.dist-info/top_level.txt
odoo10_addon_stock_lot_note-10.0.1.0.0.99.dev3.dist-info/RECORD
